AllMeans/__init__.py
AllMeans/api.py
AllMeans/cli.py
AllMeans/algorithms/__init__.py
AllMeans/algorithms/clustering.py
AllMeans/core/__init__.py
AllMeans/core/features.py
AllMeans/core/labeling.py
AllMeans/core/pipeline.py
AllMeans/core/types.py
AllMeans/evaluation/__init__.py
AllMeans/evaluation/metrics.py
allmeans-2.0.0.dist-info/METADATA
allmeans-2.0.0.dist-info/WHEEL
allmeans-2.0.0.dist-info/entry_points.txt
allmeans-2.0.0.dist-info/licenses/LICENSE
allmeans-2.0.0.dist-info/RECORD
