Metadata-Version: 2.4
Name: allmeans
Version: 2.0.0
Summary: Automatic topic discovery with zero LLMs, minimal input
Project-URL: Homepage, https://github.com/kmaurinjones/AllMeans
Project-URL: Documentation, https://github.com/kmaurinjones/AllMeans
Project-URL: Repository, https://github.com/kmaurinjones/AllMeans
Project-URL: Issues, https://github.com/kmaurinjones/AllMeans/issues
Author: Kai Maurin-Jones
License: MIT License
License-File: LICENSE
Classifier: Development Status :: 4 - Beta
Classifier: Intended Audience :: Developers
Classifier: Intended Audience :: Science/Research
Classifier: License :: OSI Approved :: MIT License
Classifier: Programming Language :: Python :: 3
Classifier: Programming Language :: Python :: 3.10
Classifier: Programming Language :: Python :: 3.11
Classifier: Programming Language :: Python :: 3.12
Classifier: Programming Language :: Python :: 3.13
Classifier: Topic :: Scientific/Engineering :: Artificial Intelligence
Classifier: Topic :: Text Processing :: Linguistic
Requires-Python: >=3.10
Requires-Dist: beautifulsoup4>=4.14.2
Requires-Dist: gensim>=4.3.0
Requires-Dist: hdbscan>=0.8.38
Requires-Dist: jellyfish>=1.0.0
Requires-Dist: matplotlib>=3.9.0
Requires-Dist: nltk>=3.8.1
Requires-Dist: numpy>=1.26.0
Requires-Dist: polars>=1.5.0
Requires-Dist: pyyaml>=6.0.0
Requires-Dist: rich>=13.0.0
Requires-Dist: scikit-learn>=1.5.0
Requires-Dist: scipy>=1.13.0
Requires-Dist: typer>=0.12.0
Requires-Dist: umap-learn>=0.5.6
Provides-Extra: all
Requires-Dist: gensim>=4.3.0; extra == 'all'
Requires-Dist: nltk>=3.9.0; extra == 'all'
Requires-Dist: plotly>=5.18.0; extra == 'all'
Requires-Dist: sentence-transformers>=2.2.2; extra == 'all'
Requires-Dist: streamlit>=1.30.0; extra == 'all'
Requires-Dist: vadersentiment>=3.3.0; extra == 'all'
Provides-Extra: dev
Requires-Dist: build>=1.0.0; extra == 'dev'
Requires-Dist: gensim>=4.3.0; extra == 'dev'
Requires-Dist: hatchling>=1.18.0; extra == 'dev'
Requires-Dist: mkdocs-material>=9.5.0; extra == 'dev'
Requires-Dist: mkdocs>=1.6.0; extra == 'dev'
Requires-Dist: mkdocstrings[python]>=0.25.0; extra == 'dev'
Requires-Dist: mypy>=1.11.0; extra == 'dev'
Requires-Dist: nltk>=3.9.0; extra == 'dev'
Requires-Dist: plotly>=5.18.0; extra == 'dev'
Requires-Dist: pre-commit>=4.0.0; extra == 'dev'
Requires-Dist: pytest-cov>=5.0.0; extra == 'dev'
Requires-Dist: pytest-xdist>=3.5.0; extra == 'dev'
Requires-Dist: pytest>=8.0.0; extra == 'dev'
Requires-Dist: ruff>=0.8.0; extra == 'dev'
Requires-Dist: sentence-transformers>=2.2.2; extra == 'dev'
Requires-Dist: streamlit>=1.30.0; extra == 'dev'
Requires-Dist: twine>=6.0.0; extra == 'dev'
Requires-Dist: vadersentiment>=3.3.0; extra == 'dev'
Provides-Extra: embeddings
Requires-Dist: gensim>=4.3.0; extra == 'embeddings'
Requires-Dist: sentence-transformers>=2.2.2; extra == 'embeddings'
Provides-Extra: sentiment
Requires-Dist: nltk>=3.9.0; extra == 'sentiment'
Requires-Dist: vadersentiment>=3.3.0; extra == 'sentiment'
Provides-Extra: viz
Requires-Dist: plotly>=5.18.0; extra == 'viz'
Requires-Dist: streamlit>=1.30.0; extra == 'viz'
